{
  "210": {
    "first_name": "John",
    "last_name": "Dorian",
    "gender": "male",
    "dob": "1980-09-13",
    "address": "1234 Sacred Heart Drive, Chicago, IL 60614",
    "telecom": "555-555-1212",
    "race": "Caucasian",
    "height": "6 ft 0 in",
    "weight": "175 lbs",
    "maritalStatus": "Single",
    "multipleBirthBoolean": false,
    "multipleBirthInteger": 1,
    "photo": "placeholder_patient_photo.png",
    "communication": {
      "language": "English",
      "preferred": true
    },
    "contact": {
      "relationship": "Emergency Contact",
      "name": "Christopher Turk",
      "telecom": "555-555-9999",
      "address": "5678 Sacred Heart Drive, Chicago, IL 60614",
      "gender": "male",
      "organization": "N/A",
      "period_start": "2000-01-01",
      "period_end": "ongoing"
    },
    "provider": {
      "generalPractitioner": "Dr. Christopher Turk, MD",
      "managingOrganization": "Sacred Heart Hospital"
    },
    "link": {
      "other_patient": "N/A",
      "link_type": "N/A"
    },
    "payer": {
      "payer_id": "UHC-001",
      "payer_name": "UnitedHealthcare",
      "plan_name": "Choice Plus PPO",
      "plan_type": "PPO",
      "group_id": "GRP-12345",
      "group_name": "Sacred Heart Employees",
      "member_id": "MBR-123456789",
      "policy_number": "POL-2025-004321",
      "effective_date": "2024-01-01",
      "termination_date": "ongoing",
      "copay_amount": "$25",
      "deductible_amount": "$1500",
      "subscriber": {
        "subscriber_id": "Unknown",
        "subscriber_name": "Unknown",
        "subscriber_relationship": "Self",
        "subscriber_dob": "1980-01-01",
        "subscriber_address": "Same as Patient"
      }
    },
    "bio_narrative": "John Dorian is a 44-year-old male residing in Chicago, Illinois. He works as a medical intern and has a physically active lifestyle. He enjoys playing basketball and takes pride in maintaining a balanced diet. Recently, John began experiencing occasional chest discomfort during his busy shifts. Understanding the importance of seeking medical advice, he visited the cardiology department for a comprehensive evaluation. John has a family history of cardiovascular issues, specifically his father who suffers from hypertension, which adds to his concerns about his own cardiac health. Following a thorough evaluation, Dr. Turk recommended a myocardial perfusion imaging study (SPECT) to further investigate his symptoms, as no prior ECG or stress testing had been done. John remains optimistic about his health trajectory, committed to following medical advice, and maintains regular follow-up appointments."
  },
  "220": {
    "first_name": "Tony",
    "last_name": "Soprano",
    "gender": "male",
    "dob": "1970-08-02",
    "address": "1 Livia St, North Caldwell, NJ 07006",
    "telecom": "555-123-4567",
    "race": "Caucasian",
    "height": "5 ft 10 in",
    "weight": "220 lbs",
    "maritalStatus": "Married",
    "multipleBirthBoolean": false,
    "multipleBirthInteger": 1,
    "photo": "placeholder_patient_photo.png",
    "communication": {
      "language": "English",
      "preferred": true
    },
    "contact": {
      "relationship": "Spouse",
      "name": "Carmela Soprano",
      "telecom": "555-765-4321",
      "address": "1 Livia St, North Caldwell, NJ 07006",
      "gender": "female",
      "organization": "N/A",
      "period_start": "1995-04-01",
      "period_end": "ongoing"
    },
    "provider": {
      "generalPractitioner": "Dr. Jennifer Melfi, MD",
      "managingOrganization": "Garden State Hospital"
    },
    "link": {
      "other_patient": "N/A",
      "link_type": "N/A"
    },
    "payer": {
      "payer_id": "UHC-001",
      "payer_name": "UnitedHealthcare",
      "plan_name": "Choice Plus PPO",
      "plan_type": "PPO",
      "group_id": "GRP-12345",
      "group_name": "Garden State Health",
      "member_id": "MBR-123456789",
      "policy_number": "POL-2025-001234",
      "effective_date": "2024-01-01",
      "termination_date": "ongoing",
      "copay_amount": "$25",
      "deductible_amount": "$1500",
      "subscriber": {
        "subscriber_id": "Unknown",
        "subscriber_name": "Unknown",
        "subscriber_relationship": "Self",
        "subscriber_dob": "1980-01-01",
        "subscriber_address": "Same as Patient"
      }
    },
    "bio_narrative": "Tony Soprano is a 54-year-old male with a background in a high-stress environment. Recently diagnosed with End Stage Renal Disease, he presents with symptoms including increased fatigue and nocturia. His medical history includes a significant family history of hypertension and kidney disease, with lifestyle choices exacerbating his condition. He experiences substantial work-related stress and has been advised to make dietary modifications to improve his health outcomes. A follow-up plan for dialysis initiation is in place, reflecting the gravity of his condition."
  },
  "221": {
    "first_name": "Bernadette",
    "last_name": "Rostenkowski-Wolowitz",
    "gender": "female",
    "dob": "1989-06-15",
    "address": "2311 Los Robles Avenue, Pasadena, CA 91107",
    "telecom": "626-555-0123",
    "race": "Caucasian",
    "height": "5 ft 4 in",
    "weight": "130 lbs",
    "maritalStatus": "Married",
    "multipleBirthBoolean": false,
    "multipleBirthInteger": 1,
    "photo": "placeholder_patient_photo.png",
    "communication": {
      "language": "English",
      "preferred": true
    },
    "contact": {
      "relationship": "Spouse",
      "name": "Howard Wolowitz",
      "telecom": "626-555-9876",
      "address": "2311 Los Robles Avenue, Pasadena, CA 91107",
      "gender": "male",
      "organization": "N/A",
      "period_start": "2013-05-01",
      "period_end": "ongoing"
    },
    "provider": {
      "generalPractitioner": "Dr. Howard Wolowitz, MD",
      "managingOrganization": "Caltech Medical Clinic"
    },
    "link": {
      "other_patient": "N/A",
      "link_type": "N/A"
    },
    "payer": {
      "payer_id": "UHC-001",
      "payer_name": "UnitedHealthcare",
      "plan_name": "Choice Plus PPO",
      "plan_type": "PPO",
      "group_id": "GRP-12345",
      "group_name": "Caltech Employee Group",
      "member_id": "MBR-123456789",
      "policy_number": "POL-2025-001234",
      "effective_date": "2024-01-01",
      "termination_date": "ongoing",
      "copay_amount": "$25",
      "deductible_amount": "$500",
      "subscriber": {
        "subscriber_id": "Unknown",
        "subscriber_name": "Unknown",
        "subscriber_relationship": "Self",
        "subscriber_dob": "1980-01-01",
        "subscriber_address": "Same as Patient"
      }
    },
    "bio_narrative": "Bernadette Rostenkowski-Wolowitz is a 35-year-old female residing in Pasadena, CA, married to physicist Howard Wolowitz. She works as a microbiologist and has a well-established background in lab research. Bernadette has no significant previous medical history and maintains a healthy lifestyle. She enjoys hiking, has a keen interest in scientific advancements, and participates in local charity events. Recently, she has been experiencing episodic chest pains and palpitations that coincide with periods of stress at work. Understandably, her worries about cardiac health have led her to seek advice from her primary care physician for further evaluation. This current situation is a concern for her as she strives to balance her professional life with her family responsibilities."
  },
  "222": {
    "first_name": "Max",
    "last_name": "Black",
    "gender": "female",
    "dob": "1987-06-01",
    "address": "23 Broadway St, Brooklyn, NY 11249, USA",
    "telecom": "555-345-6789",
    "race": "Caucasian",
    "height": "5 ft 5 in",
    "weight": "140 lbs",
    "maritalStatus": "Single",
    "multipleBirthBoolean": false,
    "multipleBirthInteger": 1,
    "photo": "placeholder_patient_photo.png",
    "communication": {
      "language": "English",
      "preferred": true
    },
    "contact": {
      "relationship": "Emergency Contact",
      "name": "Caroline Channing",
      "telecom": "555-123-4567",
      "address": "23 Broadway St, Brooklyn, NY 11249, USA",
      "gender": "female",
      "organization": "N/A",
      "period_start": "2005-01-10",
      "period_end": "ongoing"
    },
    "provider": {
      "generalPractitioner": "Dr. Jane Smith",
      "managingOrganization": "Williamsburg Medical Center"
    },
    "link": {
      "other_patient": "N/A",
      "link_type": "N/A"
    },
    "payer": {
      "payer_id": "UHC-001",
      "payer_name": "UnitedHealthcare",
      "plan_name": "Choice Plus PPO",
      "plan_type": "PPO",
      "group_id": "GRP-12345",
      "group_name": "Local 123",
      "member_id": "MBR-987654321",
      "policy_number": "POL-2025-001234",
      "effective_date": "2025-01-01",
      "termination_date": "ongoing",
      "copay_amount": "$25",
      "deductible_amount": "$500",
      "subscriber": {
        "subscriber_id": "Unknown",
        "subscriber_name": "Unknown",
        "subscriber_relationship": "Self",
        "subscriber_dob": "1980-01-01",
        "subscriber_address": "Same as Patient"
      }
    },
    "bio_narrative": "Max Black, known for her witty and sarcastic sense of humor, has transitioned from her life as a waitress and joint business owner in a cupcake shop to dealing with medical concerns related to chronic kidney disease. Living in Brooklyn, New York, she manages her condition with the help of her close friend and emergency contact, Caroline Channing.\nHer lifestyle has undergone significant changes following the gradual decline in her kidney function. Max adheres to a low-sodium diet recommended by her healthcare providers, and frequently visits her general practitioner, Dr. Jane Smith, at Williamsburg Medical Center for routine check-ups and management of her CKD. Despite her health challenges, Max maintains a positive outlook on life and spends her free time enjoying Brooklyn's vibrant art scene.\nMax has no known family history of kidney disease, and her recent diagnostic tests indicate Stage 3a chronic kidney disease. Although her renal function is decreasing, current lab results do not necessitate immediate dialysis. Max is well-informed and understands that monitoring her condition closely and adhering to her healthcare plan is vital to delaying the progression of her kidney disease."
  },
  "223": {
    "first_name": "George",
    "last_name": "Costanza",
    "gender": "male",
    "dob": "1965-06-09",
    "address": "129 West 81st Street, Apartment 5A, New York, NY 10024",
    "telecom": "555-123-7800",
    "race": "Caucasian",
    "height": "5 ft 6 in",
    "weight": "180 lbs",
    "maritalStatus": "Single",
    "multipleBirthBoolean": false,
    "multipleBirthInteger": 1,
    "photo": "placeholder_patient_photo.png",
    "communication": {
      "language": "English",
      "preferred": true
    },
    "contact": {
      "relationship": "Spouse",
      "name": "Elaine Benes",
      "telecom": "555-987-6543",
      "address": "55 Central Park West, New York, NY 10023",
      "gender": "female",
      "organization": "N/A",
      "period_start": "2000-06-01",
      "period_end": "ongoing"
    },
    "provider": {
      "generalPractitioner": "Dr. Wilhelm Taylor, MD",
      "managingOrganization": "New York Presbyterian Hospital"
    },
    "link": {
      "other_patient": "N/A",
      "link_type": "N/A"
    },
    "payer": {
      "payer_id": "UHC-2025",
      "payer_name": "UnitedHealthcare",
      "plan_name": "Choice Plus PPO",
      "plan_type": "PPO",
      "group_id": "GRP-12345",
      "group_name": "Vandelay Industries",
      "member_id": "MBR-123456789",
      "policy_number": "POL-2025-012345",
      "effective_date": "2025-01-01",
      "termination_date": "ongoing",
      "copay_amount": "$30",
      "deductible_amount": "$500",
      "subscriber": {
        "subscriber_id": "Unknown",
        "subscriber_name": "Unknown",
        "subscriber_relationship": "Self",
        "subscriber_dob": "1980-01-01",
        "subscriber_address": "Same as Patient"
      }
    },
    "bio_narrative": ""
  },
  "224": {
    "first_name": "Ross",
    "last_name": "Geller",
    "gender": "male",
    "dob": "1967-10-18",
    "address": "90 Bedford St, Apt 20, New York, NY, 10014",
    "telecom": "212-555-1234",
    "race": "Caucasian",
    "height": "6 ft 1 in",
    "weight": "185 lbs",
    "maritalStatus": "Single",
    "multipleBirthBoolean": false,
    "multipleBirthInteger": 1,
    "photo": "placeholder_patient_photo.png",
    "communication": {
      "language": "English",
      "preferred": true
    },
    "contact": {
      "relationship": "Emergency Contact",
      "name": "Monica Geller",
      "telecom": "212-555-2345",
      "address": "90 Bedford St, Apt 20, New York, NY, 10014",
      "gender": "female",
      "organization": "N/A",
      "period_start": "2020-01-01",
      "period_end": "ongoing"
    },
    "provider": {
      "generalPractitioner": "Dr. Leo Markus, MD",
      "managingOrganization": "New York-Presbyterian Hospital"
    },
    "link": {
      "other_patient": "N/A",
      "link_type": "N/A"
    },
    "payer": {
      "payer_id": "UHC-001",
      "payer_name": "UnitedHealthcare",
      "plan_name": "Choice Plus PPO",
      "plan_type": "PPO",
      "group_id": "GRP-12345",
      "group_name": "Paleontology Society",
      "member_id": "MBR-987654321",
      "policy_number": "POL-2025-000001",
      "effective_date": "2024-01-01",
      "termination_date": "ongoing",
      "copay_amount": "$30",
      "deductible_amount": "$1500",
      "subscriber": {
        "subscriber_id": "Unknown",
        "subscriber_name": "Unknown",
        "subscriber_relationship": "Self",
        "subscriber_dob": "1980-01-01",
        "subscriber_address": "Same as Patient"
      }
    },
    "bio_narrative": ""
  },
  "225": {
    "first_name": "Meredith",
    "last_name": "Grey",
    "gender": "female",
    "dob": "1978-11-10",
    "address": "123 Hospital Drive, Seattle, WA 98101",
    "telecom": "206-555-0199",
    "race": "Caucasian",
    "height": "5 ft 5 in",
    "weight": "135 lbs",
    "maritalStatus": "Single",
    "multipleBirthBoolean": false,
    "multipleBirthInteger": 1,
    "photo": "placeholder_patient_photo.png",
    "communication": {
      "language": "English",
      "preferred": true
    },
    "contact": {
      "relationship": "Emergency Contact",
      "name": "Derek Shepherd",
      "telecom": "206-555-0100",
      "address": "123 Hospital Drive, Seattle, WA 98101",
      "gender": "male",
      "organization": "N/A",
      "period_start": "2005-04-15",
      "period_end": "ongoing"
    },
    "provider": {
      "generalPractitioner": "Dr. Miranda Bailey, MD",
      "managingOrganization": "Seattle Grace Hospital"
    },
    "link": {
      "other_patient": "N/A",
      "link_type": "N/A"
    },
    "payer": {
      "payer_id": "UHC-002",
      "payer_name": "UnitedHealthcare",
      "plan_name": "Choice Plus PPO",
      "plan_type": "PPO",
      "group_id": "GRP-12345",
      "group_name": "Seattle Medical Group",
      "member_id": "MBR-123456789",
      "policy_number": "POL-2025-123456",
      "effective_date": "2024-01-01",
      "termination_date": "ongoing",
      "copay_amount": "$25",
      "deductible_amount": "$500",
      "subscriber": {
        "subscriber_id": "Unknown",
        "subscriber_name": "Unknown",
        "subscriber_relationship": "Self",
        "subscriber_dob": "1980-01-01",
        "subscriber_address": "Same as Patient"
      }
    },
    "bio_narrative": "Meredith Grey is a seasoned and highly skilled surgeon at Seattle Grace Hospital, known for her dedication and exceptional surgical skills. She was born and raised in Seattle, Washington, and has a notable family history in medicine. Her mother, Ellis Grey, was a world-renowned surgeon and this legacy has been a significant driving force in Meredith's career.\n\nMedically, Meredith has faced numerous personal and professional challenges. She has a history of overcoming significant personal adversities which has fortified her resolve and determination to excel in her field. Her social history reflects a deep commitment to her profession, maintaining close relationships with her colleagues whom she considers as her family.\n\nDue to her extensive experience in the surgical field, Meredith is well aware of the implications of undergoing a liver transplant, given her diagnosis of cirrhosis. She has expressed a firm understanding of the procedure and the required postoperative care, which is crucial for a successful recovery. Despite the stigma and challenges of liver disease, her resilient personality and family support system make her a strong candidate for the transplantation process."
  }
}